setup.py
multicpu/__init__.py
multicpu/multicpu.py
multicpu.egg-info/PKG-INFO
multicpu.egg-info/SOURCES.txt
multicpu.egg-info/dependency_links.txt
multicpu.egg-info/top_level.txt
test/test.py