Metadata-Version: 1.0
Name: multicpu
Version: 1.0.3
Summary: Use multicpu, you can let you program run in multi-cpu and you can also set the number of threads in each cpu.
Home-page: https://github.com/cyh_24/multicpu
Author: cyh_24
Author-email: cyh@buaa.edu.cn
License: MIT License (SEE LICENSE)
Platform: UNKNOWN
